testuL/__init__.py
testuL/mapSKU.py
testuL-0.0.12.dist-info/LICENSE
testuL-0.0.12.dist-info/METADATA
testuL-0.0.12.dist-info/WHEEL
testuL-0.0.12.dist-info/top_level.txt
testuL-0.0.12.dist-info/RECORD
